cleanup_py/__init__.py
cleanup_py/_cleanup.py
cleanup_py/_find.py
cleanup_py/cleanup.py
cleanup_py/command.py
cleanup_py/tests/__init__.py
cleanup_py/tests/cleanup_test.py
cleanup_py-0.1.33.dist-info/LICENSE
cleanup_py-0.1.33.dist-info/METADATA
cleanup_py-0.1.33.dist-info/WHEEL
cleanup_py-0.1.33.dist-info/entry_points.txt
cleanup_py-0.1.33.dist-info/top_level.txt
cleanup_py-0.1.33.dist-info/RECORD
